{"cameraMode":{"drawMode":0,"name":"Shaded","section":"Shading Mode"},"sceneLighting":true,"audioPlay":false,"sceneViewState":{"m_AlwaysRefresh":false,"showFog":true,"showSkybox":true,"showFlares":true,"showImageEffects":true,"showParticleSystems":true,"showVisualEffectGraphs":true,"m_FxEnabled":true},"in2DMode":false,"pivot":{"x":1.2616721391677857,"y":20.275009155273439,"z":4.048379421234131},"rotation":{"x":0.12049110978841782,"y":0.34739574790000918,"z":-0.04506439343094826,"w":0.9288530349731445},"size":8.401715278625489,"orthographic":false}